{"class":"TSStatic","persistentId":"9a95a7e4-c526-46b9-97ae-91f9604de810","__parent":"fs_6_sign_old","position":[-231.841095,-60.5021248,120.754646],"hidden":true,"isRenderEnabled":false,"rotationMatrix":[-0.00555956364,-0.999984682,0,0.999984682,-0.00555956364,0,0,0,1],"shapeName":"/levels/west_coast_usa/art/shapes/buildings/s_mascot.dae","useInstanceRenderData":true}
{"class":"TSStatic","persistentId":"9c47f9f1-c321-476c-8f77-eb290c4814ea","__parent":"fs_6_sign_old","position":[-232.472183,-60.1378822,120.952805],"hidden":true,"isRenderEnabled":false,"rotationMatrix":[-0.862593055,-0.505900323,0,0.505900323,-0.862593055,0,0,0,1],"shapeName":"/levels/west_coast_usa/art/shapes/buildings/s_fuel_charger_concrete_base.dae","useInstanceRenderData":true}
{"class":"TSStatic","persistentId":"c796c237-e6ad-43b5-bfd8-57c4b180df4c","__parent":"fs_6_sign_old","position":[-232.124222,-60.7312431,120.952805],"hidden":true,"isRenderEnabled":false,"rotationMatrix":[0.862591624,0.505900979,0,-0.505900979,0.862591624,0,0,0,1],"shapeName":"/levels/west_coast_usa/art/shapes/buildings/s_fuel_charger_concrete_base.dae","useInstanceRenderData":true}
{"class":"TSStatic","persistentId":"8694f3da-0cd8-4fa8-bddd-75e905061765","__parent":"fs_6_sign_old","position":[-231.774567,-61.3274231,120.952805],"hidden":true,"isRenderEnabled":false,"rotationMatrix":[-0.862593055,-0.505900323,0,0.505900323,-0.862593055,0,0,0,1],"shapeName":"/levels/west_coast_usa/art/shapes/buildings/s_fuel_charger_concrete_base.dae","useInstanceRenderData":true}
{"class":"TSStatic","persistentId":"251278d2-f5de-45ea-a5fa-e1d29e08167e","__parent":"fs_6_sign_old","position":[-230.914581,-60.82304,120.952805],"hidden":true,"isRenderEnabled":false,"rotationMatrix":[0.862591743,0.505900741,0,-0.505900741,0.862591743,0,0,0,1],"shapeName":"/levels/west_coast_usa/art/shapes/buildings/s_fuel_charger_concrete_base.dae","useInstanceRenderData":true}
{"class":"TSStatic","persistentId":"0e1b319d-8d62-47c6-8800-684b427c4d38","__parent":"fs_6_sign_old","position":[-231.612244,-59.6335068,120.952805],"hidden":true,"isRenderEnabled":false,"rotationMatrix":[0.862591743,0.505900741,0,-0.505900741,0.862591743,0,0,0,1],"shapeName":"/levels/west_coast_usa/art/shapes/buildings/s_fuel_charger_concrete_base.dae","useInstanceRenderData":true}
{"class":"TSStatic","persistentId":"85d16381-12fc-49f8-9347-dc12195f08d3","__parent":"fs_6_sign_old","position":[-231.262589,-60.2296867,120.952805],"hidden":true,"isRenderEnabled":false,"rotationMatrix":[-0.862592101,-0.505900741,0,0.505900741,-0.862592101,0,0,0,1],"shapeName":"/levels/west_coast_usa/art/shapes/buildings/s_fuel_charger_concrete_base.dae","useInstanceRenderData":true}
